setup.py
NlpToolkit_SequenceProcessing.egg-info/PKG-INFO
NlpToolkit_SequenceProcessing.egg-info/SOURCES.txt
NlpToolkit_SequenceProcessing.egg-info/dependency_links.txt
NlpToolkit_SequenceProcessing.egg-info/requires.txt
NlpToolkit_SequenceProcessing.egg-info/top_level.txt
SequenceProcessing/__init__.py
SequenceProcessing/Classification/GatedRecurrentUnitModel.py
SequenceProcessing/Classification/LongShortTermMemoryModel.py
SequenceProcessing/Classification/Model.py
SequenceProcessing/Classification/RecurrentNeuralNetworkModel.py
SequenceProcessing/Classification/__init__.py
SequenceProcessing/Initializer/Initializer.py
SequenceProcessing/Initializer/Random.py
SequenceProcessing/Initializer/UniformXavier.py
SequenceProcessing/Initializer/__init__.py
SequenceProcessing/Sequence/LabelledSentence.py
SequenceProcessing/Sequence/LabelledVectorizedWord.py
SequenceProcessing/Sequence/SequenceCorpus.py
SequenceProcessing/Sequence/__init__.py