Metadata-Version: 2.1
Name: NlpToolkit-SequenceProcessing
Version: 1.0.0
Summary: Sequence Processing library
Home-page: https://github.com/StarlangSoftware/SequenceProcessing-Py
Author: olcaytaner
Author-email: olcay.yildiz@ozyegin.edu.tr
